LICENSE
MANIFEST.in
README.md
setup.cfg
setup.py
http_math_server.egg-info/PKG-INFO
http_math_server.egg-info/SOURCES.txt
http_math_server.egg-info/dependency_links.txt
http_math_server.egg-info/top_level.txt
src/__init__.py
src/calculation.py
src/config.py
src/http_server.py
src/models.py
src/socket_server.py
src/templates/__init__.py
src/templates/database.html
src/templates/index.html
src/templates/limit_and_offset.html
src/templates/__pycache__/__init__.cpython-310.pyc
test/test_module.py