Metadata-Version: 2.1
Name: http-math-server
Version: 1.0
Summary: Example of math server
Home-page: UNKNOWN
Author: Aleksey
Author-email: aleksisgreeby@mail.ru
License: UNKNOWN
Platform: UNKNOWN
Classifier: Programming Language :: Python :: 3
Classifier: License :: OSI Approved :: MIT License
Classifier: Operating System :: OS Independent
License-File: LICENSE
